openkoppeltaal/__init__.py
openkoppeltaal/cli.py
openkoppeltaal/commands.py
openkoppeltaal/py.typed
openkoppeltaal/settings.py
openkoppeltaal-0.1.1.dist-info/entry_points.txt
openkoppeltaal-0.1.1.dist-info/LICENSE
openkoppeltaal-0.1.1.dist-info/WHEEL
openkoppeltaal-0.1.1.dist-info/METADATA
openkoppeltaal-0.1.1.dist-info/RECORD
