Metadata-Version: 2.1
Name: openkoppeltaal
Version: 0.1.1
Summary: openkoppeltaal 
Author-email: DK <tk@terminalkitten.com>
Classifier: License :: OSI Approved :: MIT License
Requires-Dist: typing-extensions
Requires-Dist: pydantic
Requires-Dist: click
Requires-Dist: fastapi
Requires-Dist: fhir.resources
Requires-Dist: uvicorn[standard]
Requires-Dist: devtools
Requires-Dist: pyfiglet
Requires-Dist: wasabi
Requires-Dist: toml
Requires-Dist: black ; extra == "dev"
Requires-Dist: ipdb ; extra == "dev"
Requires-Dist: ipython ; extra == "dev"
Requires-Dist: flit ; extra == "dev"
Requires-Dist: flake8 ; extra == "dev"
Requires-Dist: pre-commit ; extra == "dev"
Requires-Dist: pytest ; extra == "dev"
Requires-Dist: mypy ; extra == "dev"
Requires-Dist: isort ; extra == "dev"
Requires-Dist: wheel ; extra == "dev"
Requires-Dist: pdoc3 ; extra == "doc"
Project-URL: Home, https://github.com/openkoppeltaal
Provides-Extra: dev
Provides-Extra: doc
